pyprofyler/__init__.py
pyprofyler-2.0.1.dist-info/licenses/LICENSE
pyprofyler-2.0.1.dist-info/METADATA
pyprofyler-2.0.1.dist-info/WHEEL
pyprofyler-2.0.1.dist-info/top_level.txt
pyprofyler-2.0.1.dist-info/RECORD
